superloop/__init__.py
superloop/auditcreeper.py
superloop/auditdiff.py
superloop/auditdiff_engine.py
superloop/confirm.py
superloop/directory.py
superloop/exec_cmd.py
superloop/get_property.py
superloop/initialize.py
superloop/modifydb.py
superloop/multithread.py
superloop/node_create.py
superloop/node_list.py
superloop/parse_cmd.py
superloop/policies.py
superloop/processdb.py
superloop/pull_cfgs.py
superloop/push_acl.py
superloop/push_cfgs.py
superloop/push_local.py
superloop/remediate.py
superloop/render.py
superloop/render_config.py
superloop/search.py
superloop/snmp.py
superloop/snmp_helper.py
superloop/ssh_connect.py
superloop/superloop.py
superloop/lib/__init__.py
superloop/lib/objects/__init__.py
superloop/lib/objects/basenode.py
superloop-1.0.4.dist-info/DESCRIPTION.rst
superloop-1.0.4.dist-info/METADATA
superloop-1.0.4.dist-info/RECORD
superloop-1.0.4.dist-info/WHEEL
superloop-1.0.4.dist-info/metadata.json
superloop-1.0.4.dist-info/top_level.txt
