Metadata-Version: 2.0
Name: superloop
Version: 1.0.4
Summary: Inspired by a wide array of toolsets (unamed) used and developed by a leading social media tech company in the Bay Area for network automation, I have attempted to create my own version.
Home-page: https://github.com/superloopnetwork/superloop
Author: Wai Lit Loi
Author-email: wailit@gmail.com
License: MIT
Download-URL: https://github.com/superloopnetwork/superloop/archive/v_1.0.4.tar.gz
Keywords: NETWORK AUTOMATION,SUPERLOOP,AUTOMATION
Platform: UNKNOWN
Classifier: Development Status :: 3 - Alpha
Classifier: Intended Audience :: Developers
Classifier: Topic :: Software Development :: Build Tools
Classifier: License :: OSI Approved :: MIT License
Classifier: Programming Language :: Python :: 3
Classifier: Programming Language :: Python :: 3.4
Classifier: Programming Language :: Python :: 3.5
Classifier: Programming Language :: Python :: 3.6
Requires-Dist: argparse
Requires-Dist: ciscoconfparse
Requires-Dist: commentjson
Requires-Dist: f5-sdk
Requires-Dist: jinja2
Requires-Dist: netmiko
Requires-Dist: pysnmp
Requires-Dist: pyyaml
